kaiba/__init__.py
kaiba/casting/__init__.py
kaiba/casting/_cast_to_date.py
kaiba/casting/_cast_to_decimal.py
kaiba/casting/_cast_to_integer.py
kaiba/collection_handlers.py
kaiba/constants.py
kaiba/functions.py
kaiba/handlers.py
kaiba/iso.py
kaiba/mapper.py
kaiba/models/__init__.py
kaiba/models/attribute.py
kaiba/models/base.py
kaiba/models/branching_object.py
kaiba/models/casting.py
kaiba/models/data_fetcher.py
kaiba/models/if_statement.py
kaiba/models/iterator.py
kaiba/models/kaiba_object.py
kaiba/models/regex.py
kaiba/models/slicing.py
kaiba/process.py
kaiba/py.typed
kaiba-3.0.1.dist-info/LICENSE
kaiba-3.0.1.dist-info/METADATA
kaiba-3.0.1.dist-info/WHEEL
kaiba-3.0.1.dist-info/RECORD
