Metadata-Version: 2.1
Name: kaiba
Version: 3.0.1
Summary: Configurable and documentable Json transformation and mapping
Home-page: https://github.com/kaiba-tech/kaiba
License: MIT
Keywords: Json mapping,data transformation,json to json,dict to dict,configurable
Author: Thomas Borgen
Author-email: thomas.borgen@greenbird.com
Requires-Python: >=3.8.1,<4.0.0
Classifier: Development Status :: 5 - Production/Stable
Classifier: Intended Audience :: Developers
Classifier: License :: OSI Approved :: MIT License
Classifier: Operating System :: OS Independent
Classifier: Programming Language :: Python :: 3
Classifier: Programming Language :: Python :: 3.9
Classifier: Programming Language :: Python :: 3.10
Classifier: Programming Language :: Python :: 3.11
Classifier: Programming Language :: Python :: 3.12
Classifier: Topic :: Software Development :: Libraries :: Python Modules
Classifier: Topic :: Utilities
Requires-Dist: pycountry (>=20.7.3,<23.0.0)
Requires-Dist: pydantic (>=2.4.2,<3.0.0)
Requires-Dist: returns (>=0.22.0,<0.23.0)
Project-URL: Documentation, https://kaiba-tech.github.io/kaiba/
Project-URL: Repository, https://github.com/kaiba-tech/kaiba
